{
  "updated": "2026-05-01 14:19:05",
  "data": {
    "^VIX": {
      "price": 16.57,
      "change": -0.32,
      "changePct": -1.8946,
      "high52": 35.3,
      "low52": 13.38,
      "volume": 0,
      "currency": "USD",
      "name": "CBOE Volatility Index",
      "ath": 59.89,
      "athDate": "2008-10-01"
    },
    "^DJI": {
      "price": 49952.92,
      "change": 300.7794,
      "changePct": 0.6058,
      "high52": 50512.79,
      "low52": 40759.41,
      "volume": 110313116,
      "currency": "USD",
      "name": "Dow Jones Industrial Average",
      "ath": 49954.49,
      "athDate": "2026-05-01"
    },
    "^NDX": {
      "price": 27735.594,
      "change": 283.4749,
      "changePct": 1.0326,
      "high52": 27777.152,
      "low52": 19605.07,
      "volume": 279493536,
      "currency": "USD",
      "name": "NASDAQ-100",
      "ath": 27735.59,
      "athDate": "2026-05-01"
    },
    "^GSPC": {
      "price": 7265.59,
      "change": 56.5802,
      "changePct": 0.7849,
      "high52": 7270.19,
      "low52": 5578.64,
      "volume": 540099551,
      "currency": "USD",
      "name": "S&P 500",
      "ath": 7265.59,
      "athDate": "2026-05-01"
    },
    "^RUT": {
      "price": 2802.626,
      "change": 2.7161,
      "changePct": 0.097,
      "high52": 2817.96,
      "low52": 1976.86,
      "volume": 0,
      "currency": "USD",
      "name": " Russell 2000 Index",
      "ath": 2802.63,
      "athDate": "2026-05-01"
    },
    "VWRA.L": {
      "price": 182.88,
      "change": 2.26,
      "changePct": 1.2512,
      "high52": 202.3,
      "low52": 139.36,
      "volume": 78531,
      "currency": "USD",
      "name": "Vanguard FTSE All-World UCITS ETF",
      "ath": 182.88,
      "athDate": "2026-05-01"
    },
    "XNAS.L": {
      "price": 64.28,
      "change": 1.06,
      "changePct": 1.6767,
      "high52": 64.28,
      "low52": 45.4,
      "volume": 11589,
      "currency": "USD",
      "name": "Xtrackers NASDAQ 100 UCITS ETF 1C",
      "ath": 64.28,
      "athDate": "2026-05-01"
    },
    "USDSGD=X": {
      "price": 1.2709,
      "change": null,
      "changePct": null,
      "high52": 1.3121,
      "low52": 1.2588,
      "volume": 0,
      "currency": "SGD",
      "name": "USD/SGD",
      "ath": 1.72,
      "athDate": "2004-05-31"
    },
    "C6L.SI": {
      "price": 6.29,
      "change": 0.0,
      "changePct": 0.0,
      "high52": 7.63,
      "low52": 6.23,
      "volume": 8606200,
      "currency": "SGD",
      "name": "Singapore Airlines Limited",
      "ath": 13.81,
      "athDate": "2007-09-30"
    },
    "U11.SI": {
      "price": 36.15,
      "change": -0.0,
      "changePct": -0.0,
      "high52": 39.5,
      "low52": 33.25,
      "volume": 2999200,
      "currency": "SGD",
      "name": "United Overseas Bank Limited",
      "ath": 38.27,
      "athDate": "2025-12-31"
    },
    "D05.SI": {
      "price": 58.5,
      "change": 0.0,
      "changePct": 0.0,
      "high52": 60.0,
      "low52": 42.5,
      "volume": 15409700,
      "currency": "SGD",
      "name": "DBS Group Holdings Ltd",
      "ath": 59.2,
      "athDate": "2025-12-31"
    },
    "O39.SI": {
      "price": 21.9,
      "change": 0.0,
      "changePct": 0.0,
      "high52": 23.1,
      "low52": 15.8,
      "volume": 7767500,
      "currency": "SGD",
      "name": "Oversea-Chinese Banking Corporation Limited",
      "ath": 21.97,
      "athDate": "2026-02-28"
    },
    "HST": {
      "price": 21.25,
      "change": 0.12,
      "changePct": 0.5679,
      "high52": 21.55,
      "low52": 14.37,
      "volume": 567226,
      "currency": "USD",
      "name": "Host Hotels & Resorts, Inc.",
      "ath": 35.87,
      "athDate": "1987-06-01"
    },
    "BBY": {
      "price": 60.32,
      "change": -0.17,
      "changePct": -0.281,
      "high52": 84.99,
      "low52": 58.18,
      "volume": 224010,
      "currency": "USD",
      "name": "Best Buy Co., Inc.",
      "ath": 114.98,
      "athDate": "2021-04-01"
    },
    "NET": {
      "price": 210.495,
      "change": 5.525,
      "changePct": 2.6955,
      "high52": 260.0,
      "low52": 120.455,
      "volume": 551864,
      "currency": "USD",
      "name": "Cloudflare, Inc.",
      "ath": 253.3,
      "athDate": "2025-10-27"
    },
    "T": {
      "price": 26.225,
      "change": 0.095,
      "changePct": 0.3636,
      "high52": 29.79,
      "low52": 22.95,
      "volume": 4678124,
      "currency": "USD",
      "name": "AT&T Inc.",
      "ath": 43.57,
      "athDate": "2000-08-01"
    },
    "UNH": {
      "price": 369.14,
      "change": -1.34,
      "changePct": -0.3617,
      "high52": 409.7,
      "low52": 234.6,
      "volume": 779696,
      "currency": "USD",
      "name": "UnitedHealth Group Incorporated",
      "ath": 584.68,
      "athDate": "2024-07-01"
    },
    "BBAI": {
      "price": 3.935,
      "change": -0.045,
      "changePct": -1.1307,
      "high52": 9.39,
      "low52": 2.96,
      "volume": 9506965,
      "currency": "USD",
      "name": "BigBear.ai Holdings, Inc.",
      "ath": 12.63,
      "athDate": "2022-04-11"
    },
    "NKE": {
      "price": 44.65,
      "change": 0.29,
      "changePct": 0.6537,
      "high52": 80.17,
      "low52": 42.09,
      "volume": 1879139,
      "currency": "USD",
      "name": "NIKE, Inc.",
      "ath": 169.24,
      "athDate": "2021-09-01"
    },
    "HPQ": {
      "price": 20.795,
      "change": -0.065,
      "changePct": -0.3116,
      "high52": 29.55,
      "low52": 17.56,
      "volume": 1638489,
      "currency": "USD",
      "name": "HP Inc.",
      "ath": 37.67,
      "athDate": "2021-10-01"
    },
    "PFE": {
      "price": 26.475,
      "change": -0.225,
      "changePct": -0.8427,
      "high52": 28.75,
      "low52": 21.97,
      "volume": 6434850,
      "currency": "USD",
      "name": "Pfizer Inc.",
      "ath": 53.73,
      "athDate": "2021-09-01"
    },
    "SPY": {
      "price": 724.285,
      "change": 5.625,
      "changePct": 0.7827,
      "high52": 724.66,
      "low52": 556.04,
      "volume": 8106913,
      "currency": "USD",
      "name": "State Street SPDR S&P 500 ETF Trust",
      "ath": 724.28,
      "athDate": "2026-05-01"
    }
  },
  "movers": {
    "NVDA": {
      "name": "NVIDIA Corporation",
      "price": 199.51,
      "currency": "USD",
      "dailyPct": -0.03,
      "week1Pct": -4.21,
      "week2Pct": -1.08,
      "week4Pct": 12.47,
      "sma200": 183.86,
      "vsSma200Pct": 8.51,
      "high52": 216.83,
      "low52": 110.82
    },
    "AMD": {
      "name": "Advanced Micro Devices, Inc.",
      "price": 353.78,
      "currency": "USD",
      "dailyPct": -0.2,
      "week1Pct": 1.72,
      "week2Pct": 27.08,
      "week4Pct": 62.66,
      "sma200": 211.35,
      "vsSma200Pct": 67.39,
      "high52": 358.235,
      "low52": 96.88
    },
    "TSLA": {
      "name": "Tesla, Inc.",
      "price": 384.82,
      "currency": "USD",
      "dailyPct": 0.84,
      "week1Pct": 2.26,
      "week2Pct": -3.94,
      "week4Pct": 6.72,
      "sma200": 402.46,
      "vsSma200Pct": -4.38,
      "high52": 498.83,
      "low52": 271.0
    },
    "PLTR": {
      "name": "Palantir Technologies Inc.",
      "price": 141.62,
      "currency": "USD",
      "dailyPct": 1.8,
      "week1Pct": -1.03,
      "week2Pct": -3.26,
      "week4Pct": -4.61,
      "sma200": 164.28,
      "vsSma200Pct": -13.79,
      "high52": 207.52,
      "low52": 105.32
    },
    "META": {
      "name": "Meta Platforms, Inc.",
      "price": 612.94,
      "currency": "USD",
      "dailyPct": 0.17,
      "week1Pct": -9.2,
      "week2Pct": -10.98,
      "week4Pct": 6.7,
      "sma200": 678.3,
      "vsSma200Pct": -9.64,
      "high52": 796.25,
      "low52": 520.26
    },
    "MSFT": {
      "name": "Microsoft Corporation",
      "price": 411.44,
      "currency": "USD",
      "dailyPct": 0.9,
      "week1Pct": -3.1,
      "week2Pct": -2.68,
      "week4Pct": 10.17,
      "sma200": 467.99,
      "vsSma200Pct": -12.08,
      "high52": 555.45,
      "low52": 356.28
    },
    "GOOGL": {
      "name": "Alphabet Inc.",
      "price": 384.73,
      "currency": "USD",
      "dailyPct": -0.02,
      "week1Pct": 11.71,
      "week2Pct": 12.6,
      "week4Pct": 30.08,
      "sma200": 281.13,
      "vsSma200Pct": 36.85,
      "high52": 385.84,
      "low52": 147.84
    },
    "AMZN": {
      "name": "Amazon.com, Inc.",
      "price": 270.98,
      "currency": "USD",
      "dailyPct": 2.23,
      "week1Pct": 2.65,
      "week2Pct": 8.15,
      "week4Pct": 29.18,
      "sma200": 227.39,
      "vsSma200Pct": 19.17,
      "high52": 273.88,
      "low52": 183.85
    },
    "AVGO": {
      "name": "Broadcom Inc.",
      "price": 419.8,
      "currency": "USD",
      "dailyPct": 0.57,
      "week1Pct": -0.7,
      "week2Pct": 3.26,
      "week4Pct": 33.46,
      "sma200": 340.08,
      "vsSma200Pct": 23.44,
      "high52": 429.31,
      "low52": 195.94
    },
    "CRWD": {
      "name": "CrowdStrike Holdings, Inc.",
      "price": 447.39,
      "currency": "USD",
      "dailyPct": 0.37,
      "week1Pct": -0.17,
      "week2Pct": 5.53,
      "week4Pct": 12.09,
      "sma200": 457.52,
      "vsSma200Pct": -2.21,
      "high52": 566.9,
      "low52": 342.72
    },
    "SMCI": {
      "name": "Super Micro Computer, Inc.",
      "price": 27.86,
      "currency": "USD",
      "dailyPct": 1.68,
      "week1Pct": -4.2,
      "week2Pct": -2.45,
      "week4Pct": 19.98,
      "sma200": 37.77,
      "vsSma200Pct": -26.24,
      "high52": 62.36,
      "low52": 19.48
    },
    "MU": {
      "name": "Micron Technology, Inc.",
      "price": 540.21,
      "currency": "USD",
      "dailyPct": 4.46,
      "week1Pct": 8.75,
      "week2Pct": 18.71,
      "week4Pct": 47.5,
      "sma200": 277.01,
      "vsSma200Pct": 95.01,
      "high52": 545.91,
      "low52": 78.54
    },
    "ARM": {
      "name": "Arm Holdings plc",
      "price": 214.25,
      "currency": "USD",
      "dailyPct": 1.87,
      "week1Pct": -8.76,
      "week2Pct": 28.5,
      "week4Pct": 43.68,
      "sma200": 141.3,
      "vsSma200Pct": 51.62,
      "high52": 237.68,
      "low52": 100.02
    },
    "MRVL": {
      "name": "Marvell Technology, Inc.",
      "price": 164.34,
      "currency": "USD",
      "dailyPct": -0.49,
      "week1Pct": 0.02,
      "week2Pct": 17.65,
      "week4Pct": 53.43,
      "sma200": 88.42,
      "vsSma200Pct": 85.86,
      "high52": 170.84,
      "low52": 53.78
    },
    "NFLX": {
      "name": "Netflix, Inc.",
      "price": 93.81,
      "currency": "USD",
      "dailyPct": 0.22,
      "week1Pct": 1.49,
      "week2Pct": -3.59,
      "week4Pct": -4.91,
      "sma200": 104.17,
      "vsSma200Pct": -9.94,
      "high52": 134.115,
      "low52": 75.01
    },
    "ORCL": {
      "name": "Oracle Corporation",
      "price": 168.19,
      "currency": "USD",
      "dailyPct": 4.21,
      "week1Pct": -2.94,
      "week2Pct": -3.92,
      "week4Pct": 14.9,
      "sma200": 212.31,
      "vsSma200Pct": -20.78,
      "high52": 345.72,
      "low52": 134.57
    },
    "NOW": {
      "name": "ServiceNow, Inc.",
      "price": 88.24,
      "currency": "USD",
      "dailyPct": -0.08,
      "week1Pct": -2.14,
      "week2Pct": -8.72,
      "week4Pct": -13.49,
      "sma200": 149.95,
      "vsSma200Pct": -41.16,
      "high52": 211.478,
      "low52": 81.24
    },
    "SNOW": {
      "name": "Snowflake Inc.",
      "price": 140.6,
      "currency": "USD",
      "dailyPct": 3.03,
      "week1Pct": 0.2,
      "week2Pct": -2.35,
      "week4Pct": -7.41,
      "sma200": 207.11,
      "vsSma200Pct": -32.11,
      "high52": 280.67,
      "low52": 118.3
    },
    "COIN": {
      "name": "Coinbase Global, Inc.",
      "price": 191.79,
      "currency": "USD",
      "dailyPct": 2.14,
      "week1Pct": -3.99,
      "week2Pct": -7.05,
      "week4Pct": 11.86,
      "sma200": 264.11,
      "vsSma200Pct": -27.38,
      "high52": 444.65,
      "low52": 139.36
    },
    "SHOP": {
      "name": "Shopify Inc.",
      "price": 125.09,
      "currency": "USD",
      "dailyPct": 3.27,
      "week1Pct": -0.59,
      "week2Pct": -4.62,
      "week4Pct": 5.78,
      "sma200": 141.99,
      "vsSma200Pct": -11.9,
      "high52": 182.19,
      "low52": 88.14
    },
    "INTC": {
      "name": "Intel Corporation",
      "price": 98.61,
      "currency": "USD",
      "dailyPct": 4.37,
      "week1Pct": 19.47,
      "week2Pct": 43.96,
      "week4Pct": 95.73,
      "sma200": 40.15,
      "vsSma200Pct": 145.6,
      "high52": 99.42,
      "low52": 18.97
    },
    "LAC": {
      "name": "Lithium Americas Corp.",
      "price": 5.55,
      "currency": "USD",
      "dailyPct": -3.14,
      "week1Pct": 19.61,
      "week2Pct": 14.67,
      "week4Pct": 37.38,
      "sma200": 4.71,
      "vsSma200Pct": 17.83,
      "high52": 10.52,
      "low52": 2.47
    }
  }
}