{
  "updated": "2026-05-08 17:52:56",
  "data": {
    "^VIX": {
      "price": 17.43,
      "change": 0.35,
      "changePct": 2.0492,
      "high52": 35.3,
      "low52": 13.38,
      "volume": 0,
      "currency": "USD",
      "name": "CBOE Volatility Index",
      "ath": 59.89,
      "athDate": "2008-10-01"
    },
    "^DJI": {
      "price": 49608.77,
      "change": 11.8012,
      "changePct": 0.0238,
      "high52": 50512.79,
      "low52": 41150.73,
      "volume": 236416147,
      "currency": "USD",
      "name": "Dow Jones Industrial Average",
      "ath": 49652.14,
      "athDate": "2026-04-01"
    },
    "^NDX": {
      "price": 29146.969,
      "change": 583.0198,
      "changePct": 2.0411,
      "high52": 29205.244,
      "low52": 19984.53,
      "volume": 794310273,
      "currency": "USD",
      "name": "NASDAQ-100",
      "ath": 29146.97,
      "athDate": "2026-05-08"
    },
    "^GSPC": {
      "price": 7394.21,
      "change": 57.1001,
      "changePct": 0.7782,
      "high52": 7401.01,
      "low52": 5644.15,
      "volume": 1709177000,
      "currency": "USD",
      "name": "S&P 500",
      "ath": 7394.21,
      "athDate": "2026-05-08"
    },
    "^RUT": {
      "price": 2859.074,
      "change": 19.4441,
      "changePct": 0.6847,
      "high52": 2888.62,
      "low52": 2011.2,
      "volume": 0,
      "currency": "USD",
      "name": " Russell 2000 Index",
      "ath": 2859.07,
      "athDate": "2026-05-08"
    },
    "VWRA.L": {
      "price": 186.2,
      "change": 0.16,
      "changePct": 0.086,
      "high52": 202.3,
      "low52": 140.5,
      "volume": 113652,
      "currency": "USD",
      "name": "Vanguard FTSE All-World UCITS ETF",
      "ath": 186.2,
      "athDate": "2026-05-08"
    },
    "XNAS.L": {
      "price": 67.4,
      "change": 0.71,
      "changePct": 1.0646,
      "high52": 67.4,
      "low52": 46.25,
      "volume": 16385,
      "currency": "USD",
      "name": "Xtrackers NASDAQ 100 UCITS ETF 1C",
      "ath": 67.4,
      "athDate": "2026-05-08"
    },
    "USDSGD=X": {
      "price": 1.2669,
      "change": null,
      "changePct": null,
      "high52": 1.3096,
      "low52": 1.2588,
      "volume": 0,
      "currency": "SGD",
      "name": "USD/SGD",
      "ath": 1.72,
      "athDate": "2004-05-31"
    }
  },
  "movers": {
    "NVDA": {
      "name": "NVIDIA Corporation",
      "price": 214.99,
      "currency": "USD",
      "dailyPct": 1.65,
      "week1Pct": 8.33,
      "week2Pct": 3.23,
      "week4Pct": 13.97,
      "sma200": 184.73,
      "vsSma200Pct": 16.38,
      "high52": 217.8,
      "low52": 115.21
    },
    "AMD": {
      "name": "Advanced Micro Devices, Inc.",
      "price": 444.98,
      "currency": "USD",
      "dailyPct": 8.94,
      "week1Pct": 23.42,
      "week2Pct": 27.94,
      "week4Pct": 81.59,
      "sma200": 217.3,
      "vsSma200Pct": 104.78,
      "high52": 448.488,
      "low52": 101.6
    },
    "TSLA": {
      "name": "Tesla, Inc.",
      "price": 426.98,
      "currency": "USD",
      "dailyPct": 3.69,
      "week1Pct": 9.25,
      "week2Pct": 13.47,
      "week4Pct": 22.36,
      "sma200": 404.38,
      "vsSma200Pct": 5.59,
      "high52": 498.83,
      "low52": 273.21
    },
    "PLTR": {
      "name": "Palantir Technologies Inc.",
      "price": 135.86,
      "currency": "USD",
      "dailyPct": -0.87,
      "week1Pct": -5.7,
      "week2Pct": -5.05,
      "week4Pct": 6.09,
      "sma200": 163.92,
      "vsSma200Pct": -17.12,
      "high52": 207.52,
      "low52": 114.9
    },
    "META": {
      "name": "Meta Platforms, Inc.",
      "price": 609.65,
      "currency": "USD",
      "dailyPct": -1.16,
      "week1Pct": 0.15,
      "week2Pct": -9.69,
      "week4Pct": -3.21,
      "sma200": 675.87,
      "vsSma200Pct": -9.8,
      "high52": 796.25,
      "low52": 520.26
    },
    "MSFT": {
      "name": "Microsoft Corporation",
      "price": 415.77,
      "currency": "USD",
      "dailyPct": -1.19,
      "week1Pct": 0.32,
      "week2Pct": -2.08,
      "week4Pct": 12.11,
      "sma200": 465.67,
      "vsSma200Pct": -10.72,
      "high52": 555.45,
      "low52": 356.28
    },
    "GOOGL": {
      "name": "Alphabet Inc.",
      "price": 398.11,
      "currency": "USD",
      "dailyPct": 0.03,
      "week1Pct": 3.22,
      "week2Pct": 15.6,
      "week4Pct": 25.49,
      "sma200": 286.26,
      "vsSma200Pct": 39.07,
      "high52": 401.37,
      "low52": 152.2
    },
    "AMZN": {
      "name": "Amazon.com, Inc.",
      "price": 272.74,
      "currency": "USD",
      "dailyPct": 0.58,
      "week1Pct": 1.67,
      "week2Pct": 3.31,
      "week4Pct": 14.41,
      "sma200": 228.52,
      "vsSma200Pct": 19.35,
      "high52": 278.56,
      "low52": 191.16
    },
    "AVGO": {
      "name": "Broadcom Inc.",
      "price": 427.38,
      "currency": "USD",
      "dailyPct": 3.59,
      "week1Pct": 1.45,
      "week2Pct": 1.09,
      "week4Pct": 15.03,
      "sma200": 343.53,
      "vsSma200Pct": 24.41,
      "high52": 437.68,
      "low52": 206.52
    },
    "CRWD": {
      "name": "CrowdStrike Holdings, Inc.",
      "price": 521.57,
      "currency": "USD",
      "dailyPct": 3.13,
      "week1Pct": 14.47,
      "week2Pct": 16.39,
      "week4Pct": 37.61,
      "sma200": 457.96,
      "vsSma200Pct": 13.89,
      "high52": 566.9,
      "low52": 342.72
    },
    "SMCI": {
      "name": "Super Micro Computer, Inc.",
      "price": 35.05,
      "currency": "USD",
      "dailyPct": 4.27,
      "week1Pct": 29.4,
      "week2Pct": 20.55,
      "week4Pct": 38.78,
      "sma200": 37.27,
      "vsSma200Pct": -5.94,
      "high52": 62.36,
      "low52": 19.48
    },
    "MU": {
      "name": "Micron Technology, Inc.",
      "price": 732.29,
      "currency": "USD",
      "dailyPct": 13.25,
      "week1Pct": 35.06,
      "week2Pct": 47.43,
      "week4Pct": 74.11,
      "sma200": 290.53,
      "vsSma200Pct": 152.05,
      "high52": 742.15,
      "low52": 84.68
    },
    "ARM": {
      "name": "Arm Holdings plc",
      "price": 215.89,
      "currency": "USD",
      "dailyPct": 1.21,
      "week1Pct": 2.23,
      "week2Pct": -8.06,
      "week4Pct": 44.96,
      "sma200": 142.72,
      "vsSma200Pct": 51.27,
      "high52": 239.5,
      "low52": 100.02
    },
    "MRVL": {
      "name": "Marvell Technology, Inc.",
      "price": 167.53,
      "currency": "USD",
      "dailyPct": 4.7,
      "week1Pct": 1.56,
      "week2Pct": 1.96,
      "week4Pct": 30.38,
      "sma200": 90.76,
      "vsSma200Pct": 84.58,
      "high52": 175.8,
      "low52": 58.61
    },
    "NFLX": {
      "name": "Netflix, Inc.",
      "price": 87.58,
      "currency": "USD",
      "dailyPct": -0.76,
      "week1Pct": -4.87,
      "week2Pct": -5.26,
      "week4Pct": -14.98,
      "sma200": 103.34,
      "vsSma200Pct": -15.25,
      "high52": 134.115,
      "low52": 75.01
    },
    "ORCL": {
      "name": "Oracle Corporation",
      "price": 195.01,
      "currency": "USD",
      "dailyPct": 0.22,
      "week1Pct": 13.49,
      "week2Pct": 12.54,
      "week4Pct": 41.22,
      "sma200": 210.98,
      "vsSma200Pct": -7.57,
      "high52": 345.72,
      "low52": 134.57
    },
    "NOW": {
      "name": "ServiceNow, Inc.",
      "price": 91.44,
      "currency": "USD",
      "dailyPct": -2.3,
      "week1Pct": 0.31,
      "week2Pct": 1.41,
      "week4Pct": 10.17,
      "sma200": 147.46,
      "vsSma200Pct": -37.99,
      "high52": 211.478,
      "low52": 81.24
    },
    "SNOW": {
      "name": "Snowflake Inc.",
      "price": 150.59,
      "currency": "USD",
      "dailyPct": -2.04,
      "week1Pct": 6.8,
      "week2Pct": 7.32,
      "week4Pct": 24.34,
      "sma200": 205.42,
      "vsSma200Pct": -26.69,
      "high52": 280.67,
      "low52": 118.3
    },
    "COIN": {
      "name": "Coinbase Global, Inc.",
      "price": 195.82,
      "currency": "USD",
      "dailyPct": 1.48,
      "week1Pct": 2.39,
      "week2Pct": -1.98,
      "week4Pct": 16.66,
      "sma200": 258.81,
      "vsSma200Pct": -24.34,
      "high52": 444.65,
      "low52": 139.36
    },
    "SHOP": {
      "name": "Shopify Inc.",
      "price": 108.3,
      "currency": "USD",
      "dailyPct": -3.08,
      "week1Pct": -15.17,
      "week2Pct": -13.93,
      "week4Pct": -2.25,
      "sma200": 141.66,
      "vsSma200Pct": -23.55,
      "high52": 182.19,
      "low52": 88.9
    },
    "INTC": {
      "name": "Intel Corporation",
      "price": 124.74,
      "currency": "USD",
      "dailyPct": 13.79,
      "week1Pct": 25.22,
      "week2Pct": 51.13,
      "week4Pct": 99.97,
      "sma200": 42.34,
      "vsSma200Pct": 194.62,
      "high52": 130.57,
      "low52": 18.97
    },
    "LAC": {
      "name": "Lithium Americas Corp.",
      "price": 5.59,
      "currency": "USD",
      "dailyPct": -1.24,
      "week1Pct": -2.1,
      "week2Pct": 20.47,
      "week4Pct": 37.35,
      "sma200": 4.77,
      "vsSma200Pct": 17.19,
      "high52": 10.52,
      "low52": 2.47
    }
  }
}